MANIFEST.in
README.md
requirements.txt
setup.cfg
setup.py
inverse_covariance/__init__.py
inverse_covariance/adaptive_graph_lasso.py
inverse_covariance/inverse_covariance.py
inverse_covariance/metrics.py
inverse_covariance/model_average.py
inverse_covariance/plot_util.py
inverse_covariance/quic_graph_lasso.py
inverse_covariance/rank_correlation.py
inverse_covariance/profiling/__init__.py
inverse_covariance/profiling/cluster_graph.py
inverse_covariance/profiling/erdos_renyi_graph.py
inverse_covariance/profiling/graphs.py
inverse_covariance/profiling/lattice_graph.py
inverse_covariance/profiling/metrics.py
inverse_covariance/profiling/monte_carlo_profile.py
inverse_covariance/pyquic/Makefile
inverse_covariance/pyquic/QUIC.C
inverse_covariance/pyquic/QUIC.h
inverse_covariance/pyquic/__init__.py
inverse_covariance/pyquic/__init__.pyc
inverse_covariance/pyquic/pyquic.cpp
inverse_covariance/pyquic/pyquic.cpython-36m-darwin.so
inverse_covariance/pyquic/pyquic.pyx
inverse_covariance/pyquic/setup.py
inverse_covariance/pyquic/__pycache__/__init__.cpython-36.pyc
inverse_covariance/pyquic/build/temp.macosx-10.11-x86_64-3.6/QUIC.o
inverse_covariance/pyquic/build/temp.macosx-10.11-x86_64-3.6/pyquic.o
skggm.egg-info/PKG-INFO
skggm.egg-info/SOURCES.txt
skggm.egg-info/dependency_links.txt
skggm.egg-info/requires.txt
skggm.egg-info/top_level.txt