Metadata-Version: 1.0
Name: skggm
Version: 0.2.8
Summary: Gaussian graphical models for scikit-learn.
Home-page: https://github.com/skggm/skggm
Author: Jason Laska and Manjari Narayan
Author-email: jlaska@gmail.com
License: MIT
Platform: UNKNOWN
